README.md
setup.py
bin/liff
pyliff/__init__.py
pyliff/liff_cmd.py
pyliff/liffclient.py
pyliff.egg-info/PKG-INFO
pyliff.egg-info/SOURCES.txt
pyliff.egg-info/dependency_links.txt
pyliff.egg-info/requires.txt
pyliff.egg-info/top_level.txt
pyliff.egg-info/zip-safe