Metadata-Version: 1.1
Name: pyliff
Version: 1.0.1
Summary: pyliff is a CLI tool to let developers to setup LIFF (LINE Frontend Framework) easily
Home-page: https://github.com/wangyung/pyliff
Author: Freddie Wang
Author-email: wangyung@gmail.com
License: BSD
Keywords: liff
Platform: UNKNOWN
Classifier: Development Status :: 5 - Production/Stable
Classifier: Intended Audience :: Developers
Classifier: License :: OSI Approved :: BSD License
Classifier: Operating System :: MacOS :: MacOS X
Classifier: Operating System :: Microsoft :: Windows
Classifier: Operating System :: POSIX :: Linux
Classifier: Programming Language :: Python :: 3
Classifier: Topic :: Software Development :: Build Tools
